{
  "basics": {
    "name": "Joshua Constantino",
    "label": "Computer Programmer",
    "picture": "https://joshmcons.github.io/images/joshmcons.jpg",
    "email": "joshmcons@gmail.com",
    "phone": "808-636-3723",
    "website": "https://joshmcons.github.io",
    "summary": "Computer Programmer for the City and County of Honolulu, Emergency Services Division",
    "location": {
      "address": "",
      "postalCode": "96818",
      "city": "Honolulu",
      "countryCode": "USA",
      "region": "Hawaii"
    },
    "profiles": [
      {
        "network": "github",
        "username": "joshmcons",
        "url": "http://github.com/joshmcons"
      },
      {
        "network": "linkedin",
        "username": "joshmcons",
        "url": "http://linkedin.com/in/joshmcons"
      }
    ]
  },
  "interests": [
    {
      "name": "Software Development",
      "keywords": [
      ]
    },
    {
      "name": "Cyber Security",
      "keywords": [
      ]
    },
    {
      "name": "Web Design",
      "keywords": [
      ]
    }
  ],
  "skills": [
    {
      "name": "Languages and Frameworks",
      "level": "",
      "keywords": [
        "C",
        "C++",
        "Java",
        "Javascript",
        "Python",
        "HTML",
        "ReactJS",
      ]
    },
    {
      "name": "Toolsets/OS",
      "level": "",
      "keywords": [
        "Windows",
        "Linux",
        "Git/GitHub",
        "IntelliJ",
        "VS Code",
      ]
    }
  ],
  "education": [
    {
      "institution": "University of Hawaii, Honolulu, HI",
      "area": "Information and Computer Sciences",
      "studyType": "B.A.",
      "startDate": "2020-08",
      "endDate": "2024-05",
      "gpa": "2.87",
      "courses": [
        "ICS111: Intro to Computer Science I",
        "ICS141: Discrete Math for CS I",
        "ICS211: Intro to Computer Science II",
        "ICS212: Program Structure",
        "ICS241: Discrete Mathematics II",
        "ICS311: Algorithms",
        "ICS314: Software Engineering I",
        "ICS321: Database Systems I",
        "ICS427: Software Quality Assurance",
        "ICS451: Data Networks",
        "ENGR401: Engineering Management",
      ]
    }
  ],
  "work": [
    {
      "company": "Department of Information Technology, City and County of Honolulu",
      "position": "Computer Programmer II",
      "startDate": "2024-08",
      "endDate": "Present",
      "summary": "Computer Programmer",
      "highlights": [
        "Ensure that computer systems are up-to-date",
        "Repair system problems in an effective and timely manner",
        "Adapt to new systems and implementation of systems"
      ]
    },
    {
      "company": "Department of Defense, National Security Innovation Network",
      "position": "X-Force Fellow",
      "startDate": "2023-06",
      "endDate": "2023-08",
      "summary": "Software Developer",
      "highlights": [
        "Created a web application to optimize flight scheduling for the 25th Infantry Division",
        "Coordinated with 25th Infantry Division to further optimize the web application"
      ]
    },
    {
      "company": "Target",
      "position": "Flexible Fulfillment Expert",
      "startDate": "2018-05",
      "endDate": "Present",
      "summary": "Fulfillment Captain",
      "highlights": [
        "Properly prepare, pack and sort guest orders for shipment using correct materials",
        "Meet guest order promise times to deliver on the guest demand",
        "Took lead of the team in the absence of the team's direct and executive leadership"
      ]
    }
  ],
  "volunteer": [
    {
      "organization": "American Foundation for Suicide Prevention",
      "website": "https://supporting.afsp.org/index.cfm?fuseaction=cms.page&id=1370",
      "position": "Volunteer",
      "startDate": "2015",
      "endDate": "2017",
      "summary": "Recorded the AFJROTC unit of Moanalua High School participating in the event",
      "highlights": [
        "Walked to raise awareness of suicide prevention",
      ]
    },
  ],
  "awards": [
    {
      "title": "Distinguished Graduate",
      "date": "2017",
      "awarder": "Hawaii Air Force Junior ROTC",
      "summary": "Graduate top 10% of all graduates in the Cadet Leadership Course"
    },
    {
      "title": "National Sojourners Award",
      "date": "2017",
      "awarder": "Hawaii Air Force Junior ROTC",
      "summary": [
        "Demonstrated potential for outstanding leadership",
        "Encouraged and demonstrated ideals of Americanism by deed or conduct or both",
      ]
    },
    {
      "title": "Military Officers Association Award",
      "date": "2018",
      "awarder": "Hawaii Air Force Junior ROTC",
      "summary": [
        "Demonstrated a high degree of loyalty to the unit, school, and country",
        "Demonstrated exceptional potential for military leadership",
      ]
    },
    {
      "title": "Target Team Member Mid Year Performance Award",
      "date": "2021",
      "awarder": "Target",
      "summary": "Recognized for amazing work and outstanding performance at T2870 Ala Moana Target Store"
    }
  ],
  
  "references": [
    {
      "name": "Available upon request",
      "reference": ""
    }
  ]
}
